inference_gateway/__init__.py
inference_gateway/client.py
inference_gateway/models.py
inference_gateway-0.5.0.dist-info/licenses/LICENSE
inference_gateway-0.5.0.dist-info/METADATA
inference_gateway-0.5.0.dist-info/WHEEL
inference_gateway-0.5.0.dist-info/top_level.txt
inference_gateway-0.5.0.dist-info/RECORD
