Metadata-Version: 2.4
Name: inference-gateway
Version: 0.5.0
Summary: A Python SDK for Inference Gateway
Author-email: Eden Reich <eden.reich@gmail.com>
License: MIT License
Project-URL: Homepage, https://github.com/inference-gateway/python-sdk
Project-URL: Issues, https://github.com/inference-gateway/python-sdk/issues
Project-URL: Documentation, https://inference-gateway.github.io/docs/
Project-URL: Repository, https://github.com/inference-gateway/python-sdk
Classifier: Programming Language :: Python :: 3
Classifier: Programming Language :: Python :: 3.12
Classifier: Programming Language :: Python :: 3.13
Classifier: Operating System :: OS Independent
Classifier: Development Status :: 4 - Beta
Classifier: Intended Audience :: Developers
Classifier: License :: OSI Approved :: MIT License
Classifier: Topic :: Software Development :: Libraries :: Python Modules
Classifier: Topic :: Internet :: WWW/HTTP :: HTTP Servers
Classifier: Topic :: Scientific/Engineering :: Artificial Intelligence
Requires-Python: >=3.12
License-File: LICENSE
Requires-Dist: requests>=2.32.3
Requires-Dist: pydantic>=2.11.5
Requires-Dist: httpx>=0.28.1
Requires-Dist: typing-extensions>=4.13.2
Provides-Extra: dev
Requires-Dist: pytest>=8.3.5; extra == "dev"
Requires-Dist: pytest-cov>=6.1.1; extra == "dev"
Requires-Dist: pytest-watch>=4.2.0; extra == "dev"
Requires-Dist: black>=25.1.0; extra == "dev"
Requires-Dist: isort>=6.0.1; extra == "dev"
Requires-Dist: mypy>=1.15.0; extra == "dev"
Requires-Dist: datamodel-code-generator>=0.30.1; extra == "dev"
Requires-Dist: pre-commit>=4.2.0; extra == "dev"
Requires-Dist: types-requests>=2.32.3; extra == "dev"
Dynamic: license-file
